Metadata-Version: 2.1
Name: anupamcalculator
Version: 0.0.2
Summary: a calculator with some advanced functions
Home-page: 
Author: anupamkumar
Author-email: anupamkumar.nith@gmail.com
License: MIT
Keywords: calculator,math,arithmetic,advanced,functions
Classifier: Development Status :: 5 - Production/Stable
License-File: LICENSE.txt
